setup.py
mlutility/__init__.py
mlutility.egg-info/PKG-INFO
mlutility.egg-info/SOURCES.txt
mlutility.egg-info/dependency_links.txt
mlutility.egg-info/not-zip-safe
mlutility.egg-info/top_level.txt