Metadata-Version: 1.0
Name: mlutility
Version: 0.1.1
Summary: Some utilities for machine learning
Home-page: https://github.com/Wulala526/MLUtility
Author: Wulala
Author-email: tyhh_123@hotmail.com
License: BSD 2-Clause License
Platform: UNKNOWN
